odoo8_addon_project_issue_baseuser-8.0.1.0.0.99.dev5-py2.7-nspkg.pth
odoo8_addon_project_issue_baseuser-8.0.1.0.0.99.dev5.dist-info/METADATA
odoo8_addon_project_issue_baseuser-8.0.1.0.0.99.dev5.dist-info/RECORD
odoo8_addon_project_issue_baseuser-8.0.1.0.0.99.dev5.dist-info/WHEEL
odoo8_addon_project_issue_baseuser-8.0.1.0.0.99.dev5.dist-info/namespace_packages.txt
odoo8_addon_project_issue_baseuser-8.0.1.0.0.99.dev5.dist-info/top_level.txt
odoo_addons/project_issue_baseuser/__init__.py
odoo_addons/project_issue_baseuser/__openerp__.py
odoo_addons/project_issue_baseuser/i18n/de.po
odoo_addons/project_issue_baseuser/i18n/es.po
odoo_addons/project_issue_baseuser/i18n/project_issue_baseuser.pot
odoo_addons/project_issue_baseuser/i18n/pt.po
odoo_addons/project_issue_baseuser/i18n/sl.po
odoo_addons/project_issue_baseuser/security/ir.model.access.csv
odoo_addons/project_issue_baseuser/security/project_security.xml
odoo_addons/project_issue_baseuser/static/description/icon.png
