Metadata-Version: 2.1
Name: odoo8-addon-project-issue-baseuser
Version: 8.0.1.0.0.99.dev5
Summary: Extend Project user roles to support more complex use cases
Home-page: UNKNOWN
Author: Daniel Reis,Odoo Community Association (OCA)
Author-email: support@odoo-community.org
License: AGPL-3
Platform: UNKNOWN
Classifier: Programming Language :: Python
Classifier: Framework :: Odoo
Classifier: License :: OSI Approved :: GNU Affero General Public License v3
Requires-Python: ~=2.7
Requires-Dist: odoo8-addon-project-baseuser
Requires-Dist: odoo (<9.0a,>=8.0a)
